trade_indicator/README.md
trade_indicator/VERSION.txt
trade_indicator/__init__.py
trade_indicator/titt.py
trade_indicator/titt_plus.py
trade_indicator/titt_python2.py
trade_indicator-1.0.0.dist-info/METADATA
trade_indicator-1.0.0.dist-info/WHEEL
trade_indicator-1.0.0.dist-info/top_level.txt
trade_indicator-1.0.0.dist-info/RECORD
