Metadata-Version: 2.1
Name: trade-indicator
Version: 1.0.0
Summary: trade_indicator
Home-page: https://github.com/cedricporter/funcat
Author: Peng Meng
Author-email: 782674371@qq.com
License: Apache License v2
Classifier: Programming Language :: Python
Classifier: Operating System :: Microsoft :: Windows
Classifier: Operating System :: Unix
Classifier: Programming Language :: Python :: 2.7
Classifier: Programming Language :: Python :: 3.4
Classifier: Programming Language :: Python :: 3.5
Classifier: Programming Language :: Python :: 3.6
Classifier: Programming Language :: Python :: 3.7
Classifier: Programming Language :: Python :: 3.8
Classifier: Programming Language :: Python :: 3.9
Classifier: Programming Language :: Python :: 3.10
Requires-Python: >=3
Requires-Dist: numpy
Requires-Dist: pandas
